tap2junit/__init__.py
tap2junit/__main__.py
tap2junit/tap13.py
tap2junit-0.2.0.dist-info/METADATA
tap2junit-0.2.0.dist-info/WHEEL
tap2junit-0.2.0.dist-info/entry_points.txt
tap2junit-0.2.0.dist-info/licenses/LICENSE
tap2junit-0.2.0.dist-info/RECORD
