Metadata-Version: 2.3
Name: tap2junit
Version: 0.2.0
Summary: A utility that converts TAP version 12 and 13 to JUnit. That's it.
Project-URL: Homepage, https://github.com/nodejs/tap2junit
Project-URL: Changelog, https://github.com/nodejs/tap2junit/blob/main/CHANGELOG.md
Author-email: "Node.js contributor" <cclauss@me.com>
License: Apache-2.0
License-File: LICENSE
Keywords: junit,tap13
Classifier: Development Status :: 4 - Beta
Classifier: Intended Audience :: Developers
Classifier: License :: OSI Approved :: Apache Software License
Classifier: Programming Language :: Python :: 3
Classifier: Programming Language :: Python :: 3.7
Classifier: Programming Language :: Python :: 3.8
Classifier: Programming Language :: Python :: 3.9
Classifier: Programming Language :: Python :: 3.10
Classifier: Programming Language :: Python :: 3.11
Classifier: Topic :: Software Development :: Build Tools
Requires-Python: >=3.7
Requires-Dist: junit-xml
Requires-Dist: yamlish
Provides-Extra: dev
Requires-Dist: black; extra == 'dev'
Requires-Dist: codespell[toml]; extra == 'dev'
Requires-Dist: mypy; extra == 'dev'
Requires-Dist: pytest; extra == 'dev'
Requires-Dist: pytest-clarity; extra == 'dev'
Requires-Dist: ruff; extra == 'dev'
